ocs/__init__.py
ocs/_version.py
ocs/agent_cli.py
ocs/base.py
ocs/checkdata.py
ocs/client_cli.py
ocs/client_http.py
ocs/client_t.py
ocs/matched_client.py
ocs/ocs_agent.py
ocs/ocs_client.py
ocs/ocs_feed.py
ocs/ocs_systemd.py
ocs/ocs_twisted.py
ocs/ocsbow.py
ocs/plugin.py
ocs/rename.py
ocs/site_config.py
ocs/testing.py
ocs/agents/__init__.py
ocs/agents/ocs_plugin_standard.py
ocs/agents/aggregator/__init__.py
ocs/agents/aggregator/agent.py
ocs/agents/aggregator/drivers.py
ocs/agents/barebones/__init__.py
ocs/agents/barebones/agent.py
ocs/agents/fake_data/__init__.py
ocs/agents/fake_data/agent.py
ocs/agents/host_manager/__init__.py
ocs/agents/host_manager/agent.py
ocs/agents/host_manager/drivers.py
ocs/agents/influxdb_publisher/__init__.py
ocs/agents/influxdb_publisher/agent.py
ocs/agents/influxdb_publisher/drivers.py
ocs/agents/registry/__init__.py
ocs/agents/registry/agent.py
ocs/support/crossbar_config.json
ocs-0.11.3.dist-info/METADATA
ocs-0.11.3.dist-info/WHEEL
ocs-0.11.3.dist-info/entry_points.txt
ocs-0.11.3.dist-info/licenses/LICENSE.txt
ocs-0.11.3.dist-info/RECORD
