Metadata-Version: 2.3
Name: ocs
Version: 0.11.3
Summary: Observatory Control System
Project-URL: Bug Tracker, https://github.com/simonsobs/ocs/issues
Project-URL: Documentation, https://ocs.readthedocs.io/
Project-URL: Homepage, https://github.com/simonsobs/ocs
Project-URL: Source Code, https://github.com/simonsobs/ocs
License-File: LICENSE.txt
Classifier: Framework :: Twisted
Classifier: Intended Audience :: Science/Research
Classifier: License :: OSI Approved :: BSD License
Classifier: Programming Language :: Python :: 3
Classifier: Programming Language :: Python :: 3.7
Classifier: Programming Language :: Python :: 3.8
Classifier: Programming Language :: Python :: 3.9
Classifier: Programming Language :: Python :: 3.10
Classifier: Programming Language :: Python :: 3.11
Classifier: Topic :: Scientific/Engineering :: Astronomy
Requires-Python: >=3.7
Requires-Dist: autobahn
Requires-Dist: deprecation
Requires-Dist: importlib-metadata; python_version < '3.10'
Requires-Dist: influxdb
Requires-Dist: numpy<2.0
Requires-Dist: pyyaml
Requires-Dist: setproctitle
Requires-Dist: twisted
Provides-Extra: dev
Requires-Dist: coverage; extra == 'dev'
Requires-Dist: docker; extra == 'dev'
Requires-Dist: pytest; extra == 'dev'
Requires-Dist: pytest-cov; extra == 'dev'
Requires-Dist: pytest-docker; extra == 'dev'
Requires-Dist: pytest-twisted; extra == 'dev'
Requires-Dist: setuptools-scm; extra == 'dev'
Requires-Dist: so3g; extra == 'dev'
Provides-Extra: so3g
Requires-Dist: so3g; extra == 'so3g'
